luis_astro_analysis/__init__.py
luis_astro_analysis/cci_analyzer.py
luis_astro_analysis/cross_correlator.py
luis_astro_analysis/fits_util.py
luis_astro_analysis/ninja.py
luis_astro_analysis/pha_util.py
luis_astro_analysis/qdp_util.py
luis_astro_analysis/tess.py
luis_astro_analysis-0.0.3.dist-info/METADATA
luis_astro_analysis-0.0.3.dist-info/WHEEL
luis_astro_analysis-0.0.3.dist-info/licenses/LICENCE
luis_astro_analysis-0.0.3.dist-info/RECORD
