Metadata-Version: 2.4
Name: luis_astro_analysis
Version: 0.0.3
Summary: A small package assisting in data analysis for Xray astronomy
Author-email: Luis Eiche <luis.eiche00@gmail.de>
License-Expression: MIT
License-File: LICENCE
Classifier: Operating System :: OS Independent
Classifier: Programming Language :: Python :: 3
Requires-Python: >=3.10
Requires-Dist: astropy>=7.1.1
Requires-Dist: matplotlib>=3.10.7
Requires-Dist: numpy>=2.3.4
Requires-Dist: pandas>=2.3.3
Requires-Dist: scipy>=1.16.2
Requires-Dist: seaborn>=0.13.2
